{
  "season": 2016,
  "leagueRules": {
    "entryFee": 50,
    "newOwnerFee": null,
    "futureDeposit": null,
    "weeklyHighPayout": 10,
    "regularSeasonWeeks": null,
    "playoffPayouts": {
      "championBase": null,
      "runnerUp": null,
      "thirdPlace": null,
      "fourthPlace": null
    },
    "ringReserve": null,
    "actualRingCost": null
  },
  "managers": [
    {
      "managerName": "Matt",
      "entryFeePaid": 50,
      "newOwnerFeePaid": null,
      "futureDepositPaid": null,
      "payoutsReceived": 55,
      "balance": 5,
      "notes": [
        "Weekly: 3 ($30); Advance to Playoffs: $25; Advancing to Finals: $0; Win Finals: $0; Amount Won: $55; Total Earned: $5."
      ]
    },
    {
      "managerName": "Ben",
      "entryFeePaid": 50,
      "newOwnerFeePaid": null,
      "futureDepositPaid": null,
      "payoutsReceived": 150,
      "balance": 100,
      "notes": [
        "Weekly: 5 ($50); Advance to Playoffs: $25; Advancing to Finals: $75; Win Finals: blank in screenshot; Amount Won: $150; Total Earned: $100."
      ]
    },
    {
      "managerName": "Jeffrey",
      "entryFeePaid": 50,
      "newOwnerFeePaid": null,
      "futureDepositPaid": null,
      "payoutsReceived": 30,
      "balance": -20,
      "notes": [
        "Weekly: 1 ($10); Advance to Playoffs: $20; Advancing to Finals: $0; Win Finals: $0; Amount Won: $30; Total Earned: -$20."
      ]
    },
    {
      "managerName": "Tyrone",
      "entryFeePaid": 50,
      "newOwnerFeePaid": null,
      "futureDepositPaid": null,
      "payoutsReceived": 120,
      "balance": 70,
      "notes": [
        "Weekly: 2 ($20); Advance to Playoffs: $25; Advancing to Finals: $75; Win Finals: blank in screenshot; Amount Won: $120; Total Earned: $70."
      ]
    },
    {
      "managerName": "Ray",
      "entryFeePaid": 50,
      "newOwnerFeePaid": null,
      "futureDepositPaid": null,
      "payoutsReceived": 0,
      "balance": -50,
      "notes": [
        "Weekly: 0 ($0); Advance to Playoffs: $0; Advancing to Finals: $0; Win Finals: $0; Amount Won: $0; Total Earned: -$50."
      ]
    },
    {
      "managerName": "Loren",
      "entryFeePaid": 50,
      "newOwnerFeePaid": null,
      "futureDepositPaid": null,
      "payoutsReceived": 35,
      "balance": -15,
      "notes": [
        "Weekly: 1 ($10); Advance to Playoffs: $25; Advancing to Finals: $0; Win Finals: $0; Amount Won: $35; Total Earned: -$15."
      ]
    },
    {
      "managerName": "Rob",
      "entryFeePaid": 50,
      "newOwnerFeePaid": null,
      "futureDepositPaid": null,
      "payoutsReceived": 35,
      "balance": -15,
      "notes": [
        "Weekly: 1 ($10); Advance to Playoffs: $25; Advancing to Finals: $0; Win Finals: $0; Amount Won: $35; Total Earned: -$15."
      ]
    },
    {
      "managerName": "Bill",
      "entryFeePaid": 50,
      "newOwnerFeePaid": null,
      "futureDepositPaid": null,
      "payoutsReceived": 35,
      "balance": -15,
      "notes": [
        "Weekly: 1 ($10); Advance to Playoffs: $25; Advancing to Finals: $0; Win Finals: $0; Amount Won: $35; Total Earned: -$15."
      ]
    },
    {
      "managerName": "KW",
      "entryFeePaid": 50,
      "newOwnerFeePaid": null,
      "futureDepositPaid": null,
      "payoutsReceived": 0,
      "balance": -50,
      "notes": [
        "Weekly: 0 ($0); Advance to Playoffs: $0; Advancing to Finals: $0; Win Finals: $0; Amount Won: $0; Total Earned: -$50."
      ]
    },
    {
      "managerName": "David B",
      "entryFeePaid": 50,
      "newOwnerFeePaid": null,
      "futureDepositPaid": null,
      "payoutsReceived": 0,
      "balance": -50,
      "notes": [
        "Weekly: 0 ($0); Advance to Playoffs: $0; Advancing to Finals: $0; Win Finals: $0; Amount Won: $0; Total Earned: -$50."
      ]
    },
    {
      "managerName": "Earl",
      "entryFeePaid": 50,
      "newOwnerFeePaid": null,
      "futureDepositPaid": null,
      "payoutsReceived": 0,
      "balance": -50,
      "notes": [
        "Weekly: 0 ($0); Advance to Playoffs: $0; Advancing to Finals: $0; Win Finals: $0; Amount Won: $0; Total Earned: -$50."
      ]
    },
    {
      "managerName": "Dan",
      "entryFeePaid": 50,
      "newOwnerFeePaid": null,
      "futureDepositPaid": null,
      "payoutsReceived": 10,
      "balance": -40,
      "notes": [
        "Weekly: 1 ($10); Advance to Playoffs: $0; Advancing to Finals: $0; Win Finals: $0; Amount Won: $10; Total Earned: -$40."
      ]
    }
  ],
  "awards": [
    {
      "id": "2016-matt-weekly-payout",
      "type": "weeklyHigh",
      "managerName": "Matt",
      "amount": 30,
      "description": "3 weekly payouts at $10 each."
    },
    {
      "id": "2016-matt-advance-to-playoffs",
      "type": "other",
      "managerName": "Matt",
      "amount": 25,
      "description": "Advance to Playoffs payout."
    },
    {
      "id": "2016-ben-weekly-payout",
      "type": "weeklyHigh",
      "managerName": "Ben",
      "amount": 50,
      "description": "5 weekly payouts at $10 each."
    },
    {
      "id": "2016-ben-advance-to-playoffs",
      "type": "other",
      "managerName": "Ben",
      "amount": 25,
      "description": "Advance to Playoffs payout."
    },
    {
      "id": "2016-ben-advancing-to-finals",
      "type": "other",
      "managerName": "Ben",
      "amount": 75,
      "description": "Advancing to Finals payout."
    },
    {
      "id": "2016-jeffrey-weekly-payout",
      "type": "weeklyHigh",
      "managerName": "Jeffrey",
      "amount": 10,
      "description": "1 weekly payout at $10."
    },
    {
      "id": "2016-jeffrey-advance-to-playoffs",
      "type": "other",
      "managerName": "Jeffrey",
      "amount": 20,
      "description": "Advance to Playoffs payout shown as $20."
    },
    {
      "id": "2016-tyrone-weekly-payout",
      "type": "weeklyHigh",
      "managerName": "Tyrone",
      "amount": 20,
      "description": "2 weekly payouts at $10 each."
    },
    {
      "id": "2016-tyrone-advance-to-playoffs",
      "type": "other",
      "managerName": "Tyrone",
      "amount": 25,
      "description": "Advance to Playoffs payout."
    },
    {
      "id": "2016-tyrone-advancing-to-finals",
      "type": "other",
      "managerName": "Tyrone",
      "amount": 75,
      "description": "Advancing to Finals payout."
    },
    {
      "id": "2016-loren-weekly-payout",
      "type": "weeklyHigh",
      "managerName": "Loren",
      "amount": 10,
      "description": "1 weekly payout at $10."
    },
    {
      "id": "2016-loren-advance-to-playoffs",
      "type": "other",
      "managerName": "Loren",
      "amount": 25,
      "description": "Advance to Playoffs payout."
    },
    {
      "id": "2016-rob-weekly-payout",
      "type": "weeklyHigh",
      "managerName": "Rob",
      "amount": 10,
      "description": "1 weekly payout at $10."
    },
    {
      "id": "2016-rob-advance-to-playoffs",
      "type": "other",
      "managerName": "Rob",
      "amount": 25,
      "description": "Advance to Playoffs payout."
    },
    {
      "id": "2016-bill-weekly-payout",
      "type": "weeklyHigh",
      "managerName": "Bill",
      "amount": 10,
      "description": "1 weekly payout at $10."
    },
    {
      "id": "2016-bill-advance-to-playoffs",
      "type": "other",
      "managerName": "Bill",
      "amount": 25,
      "description": "Advance to Playoffs payout."
    },
    {
      "id": "2016-dan-weekly-payout",
      "type": "weeklyHigh",
      "managerName": "Dan",
      "amount": 10,
      "description": "1 weekly payout at $10."
    }
  ],
  "notes": [
    "Source: data/history/source-screenshots/financial/2016.png.",
    "The screenshot uses advancement-based columns: Advance to Playoffs, Advancing to Finals, and Win Finals.",
    "Jeffrey's Advance to Playoffs value is shown as $20 while the other visible playoff-advance payouts are $25.",
    "Ben and Tyrone have blank Win Finals cells in the screenshot; no championBase value is recorded.",
    "regularSeasonWeeks, newOwnerFee, futureDeposit, ringReserve, and actualRingCost are null because they are not shown."
  ]
}
